github_trending/__init__.py
github_trending/github_trending.py
github_trending_api-0.2.2.dist-info/LICENSE
github_trending_api-0.2.2.dist-info/METADATA
github_trending_api-0.2.2.dist-info/WHEEL
github_trending_api-0.2.2.dist-info/top_level.txt
github_trending_api-0.2.2.dist-info/RECORD
