Metadata-Version: 2.1
Name: github-trending-api
Version: 0.2.2
Summary: Pypi package to access Github trending in Python
Home-page: https://github.com/manjotpahwa/github-trending-api
Author: Manjot Pahwa
Author-email: manjot.pahwa@gmail.com
License: MIT
Download-URL: https://pypi.org/project/github-trending-api/
Keywords: Github,Github Trending
Platform: UNKNOWN
Requires-Dist: aiohttp
Requires-Dist: lxml
